examples/__init__.py
examples/prompts.py
pixie_prompts_examples-0.1.4.dist-info/METADATA
pixie_prompts_examples-0.1.4.dist-info/WHEEL
pixie_prompts_examples-0.1.4.dist-info/licenses/LICENSE
pixie_prompts_examples-0.1.4.dist-info/RECORD
