Metadata-Version: 2.4
Name: pixie-prompts-examples
Version: 0.1.4
Summary: examples for using pixie-prompts
License: MIT
License-File: LICENSE
Author: Yiou Li
Author-email: yol@gopixie.ai
Requires-Python: >=3.11,<3.14
Classifier: License :: OSI Approved :: MIT License
Classifier: Programming Language :: Python :: 3
Classifier: Programming Language :: Python :: 3.11
Classifier: Programming Language :: Python :: 3.12
Classifier: Programming Language :: Python :: 3.13
Requires-Dist: openai (>=2.15.0,<3.0.0)
Requires-Dist: pixie-prompts[server] (>=0.1.4,<0.2.0)
Project-URL: Changelog, https://github.com/yiouli/pixie-prompts/commits/main/
Project-URL: Documentation, https://yiouli.github.io/pixie-prompts/
Project-URL: Homepage, https://gopixie.ai
Project-URL: Issues, https://github.com/yiouli/pixie-prompts/issues
Project-URL: Repository, https://github.com/yiouli/pixie-prompts-examples
